ddgs_mcp_server/__init__.py
ddgs_mcp_server/main.py
ddgs_mcp_server/server.py
ddgs_mcp_server-0.4.1.dist-info/METADATA
ddgs_mcp_server-0.4.1.dist-info/WHEEL
ddgs_mcp_server-0.4.1.dist-info/entry_points.txt
ddgs_mcp_server-0.4.1.dist-info/licenses/LICENSE
ddgs_mcp_server-0.4.1.dist-info/RECORD
