Metadata-Version: 2.4
Name: ddgs-mcp-server
Version: 0.4.1
Summary: DuckDuckGo Search MCP Server
License-File: LICENSE
Requires-Python: >=3.10
Requires-Dist: ddgs>=9.10.0
Requires-Dist: mcp>=1.0.0
